{
  "type": "Feature",
  "properties": {
    "gn:admin1_code":"11695388.0",
    "gn:asciiname":"Te Tautua",
    "gn:cc2":"CK",
    "gn:country_code":"CK",
    "gn:dem":11,
    "gn:feature_class":"P",
    "gn:feature_code":"PPL",
    "gn:name":"Te Tautua",
    "gn:population":0,
    "gn:timezone":"Pacific/Rarotonga",
    "iso:country":"CK",
    "name:und_x_variant":[
        "Tautua",
        "Te Tautua"
    ],
    "wof:name":"Te Tautua",
    "wof:placetype":"locality"
},
  "geometry": {"coordinates":[-157.92621,-8.95873],"type":"Point"}
}