{
  "type": "Feature",
  "properties": {
    "gn:admin1_code":"0.0",
    "gn:asciiname":"Oneroa",
    "gn:cc2":"CK",
    "gn:country_code":"CK",
    "gn:dem":18,
    "gn:feature_class":"P",
    "gn:feature_code":"PPL",
    "gn:name":"Oneroa",
    "gn:population":0,
    "gn:timezone":"Pacific/Rarotonga",
    "iso:country":"CK",
    "name:fra_x_preferred":[
        "Oneroa"
    ],
    "name:pol_x_preferred":[
        "Oneroa"
    ],
    "name:und_x_variant":[
        "Temakatea Village",
        "Oneroa"
    ],
    "wof:name":"Oneroa",
    "wof:placetype":"locality"
},
  "geometry": {"coordinates":[-157.96028000000001,-21.92],"type":"Point"}
}