{
  "type": "Feature",
  "properties": {
    "gn:admin1_code":"11695385.0",
    "gn:asciiname":"Kimiangatau Village",
    "gn:country_code":"CK",
    "gn:dem":4,
    "gn:feature_class":"P",
    "gn:feature_code":"PPL",
    "gn:name":"Kimiangatau Village",
    "gn:population":0,
    "gn:timezone":"Pacific/Rarotonga",
    "iso:country":"CK",
    "name:eng_x_preferred":[
        "Kimiangatau Village"
    ],
    "wof:name":"Kimiangatau Village",
    "wof:placetype":"locality"
},
  "geometry": {"coordinates":[-157.35648,-20.14367],"type":"Point"}
}